pymapbox/__init__.py
pymapbox/dotdict.py
pymapbox/map.py
pymapbox/twomaps.py
pymapbox/utils.py
pymapbox/elections/__init__.py
pymapbox/elections/clean.py
pymapbox/elections/get.py
pymapbox/elections/show.py
pymapbox-0.0.1.dist-info/METADATA
pymapbox-0.0.1.dist-info/WHEEL
pymapbox-0.0.1.dist-info/top_level.txt
pymapbox-0.0.1.dist-info/RECORD
